deepforge/__init__.py
deepforge/__main__.py
deepforge/cnn.py
deepforge/crnn.py
deepforge/dae.py
deepforge/dnn.py
deepforge/initialize.py
deepforge/multivariateDnn.py
deepforge/rnn.py
deepforge-0.0.7.dist-info/LICENSE
deepforge-0.0.7.dist-info/METADATA
deepforge-0.0.7.dist-info/WHEEL
deepforge-0.0.7.dist-info/entry_points.txt
deepforge-0.0.7.dist-info/top_level.txt
deepforge-0.0.7.dist-info/RECORD
