Metadata-Version: 2.1
Name: deepforge
Version: 0.0.7
Summary: A python object oriented library to model deep neural networks based on Keras/Tensorflow.
Author-email: Fabrizio Romanelli <fabrizio.romanelli@gmail.com>
License: GNU GENERAL PUBLIC LICENSE
Project-URL: Homepage, https://github.com/fabrizioromanelli/deepforge
Keywords: deep learning,deep neural networks,neural networks,dnn,nn
Classifier: License :: OSI Approved :: GNU General Public License v3 (GPLv3)
Classifier: Programming Language :: Python
Classifier: Programming Language :: Python :: 3
Classifier: Development Status :: 2 - Pre-Alpha
Requires-Python: >=3.9
License-File: LICENSE
Requires-Dist: tensorflow >=2.14.0
Requires-Dist: keras >=2.14.0
Provides-Extra: dev
Requires-Dist: black ; extra == 'dev'
Requires-Dist: bumpver ; extra == 'dev'
Requires-Dist: isort ; extra == 'dev'
Requires-Dist: pip-tools ; extra == 'dev'
Requires-Dist: pytest ; extra == 'dev'
